rs_tools/__init__.py
rs_tools/dataprocessor.py
rs_tools/geo2proj.py
rs_tools/normalization.py
rs_tools/polygonize.py
rs_tools/rs3.py
openrs_python-0.1.0.dist-info/LICENSE
openrs_python-0.1.0.dist-info/METADATA
openrs_python-0.1.0.dist-info/WHEEL
openrs_python-0.1.0.dist-info/top_level.txt
openrs_python-0.1.0.dist-info/RECORD
